{
  "generated_at": "2026-04-17T01:22:34.342480+00:00",
  "count": 21,
  "data": [
    {
      "address": "0x323ED112757f8EF800afC63D0c47419CbF276268",
      "name": "tp.hl",
      "refcode": "",
      "pear": {
        "total_volume": 686852.39,
        "total_fees": 665.8487,
        "total_builder_fees": 393.0767
      },
      "referral": {
        "total_referees": 10,
        "total_referral_volume": 17729382.94,
        "referral_fee_paid": 1200.0
      },
      "last_updated": "2026-04-17T01:21:38.101176+00:00"
    },
    {
      "address": "0x2882Fc0C1cb1B997Bda58644540F731DFa00d85c",
      "name": "Coin Notes",
      "refcode": "",
      "pear": {
        "total_volume": 223770.87,
        "total_fees": 227.926,
        "total_builder_fees": 130.1477
      },
      "referral": {
        "total_referees": 3,
        "total_referral_volume": 107281.09,
        "referral_fee_paid": NaN
      },
      "last_updated": "2026-04-17T01:21:43.009500+00:00"
    },
    {
      "address": "0x373418c5b99885ce346ef2b1745c855dd129aa84",
      "name": "Blackie.hl",
      "refcode": "",
      "pear": {
        "total_volume": 8147.89,
        "total_fees": 8.5553,
        "total_builder_fees": 4.8887
      },
      "referral": {
        "total_referees": 0,
        "total_referral_volume": 0.0,
        "referral_fee_paid": NaN
      },
      "last_updated": "2026-04-17T01:21:44.450509+00:00"
    },
    {
      "address": "0xB9cDEEb253a659beC27122c7A6E4789b7CC418d7",
      "name": "Moritzpike",
      "refcode": "",
      "pear": {
        "total_volume": 2485285.04,
        "total_fees": 2538.6689,
        "total_builder_fees": 1468.2761
      },
      "referral": {
        "total_referees": 15,
        "total_referral_volume": 1149.57,
        "referral_fee_paid": 2200.0
      },
      "last_updated": "2026-04-17T01:21:50.752008+00:00"
    },
    {
      "address": "0x2d87c160aedd8ffe2b5d24e460baf51f43ea61d1",
      "name": "Hashroshin.eth",
      "refcode": "",
      "pear": {
        "total_volume": 3607853.38,
        "total_fees": 3649.1456,
        "total_builder_fees": 2145.1213
      },
      "referral": {
        "total_referees": 3,
        "total_referral_volume": 0.0,
        "referral_fee_paid": NaN
      },
      "last_updated": "2026-04-17T01:21:52.453193+00:00"
    },
    {
      "address": "0xb0431cB1f6E3f673BEeB902a91357a58582446A9",
      "name": "Lunartha",
      "refcode": "",
      "pear": {
        "total_volume": 263983.92,
        "total_fees": 252.2694,
        "total_builder_fees": 156.6818
      },
      "referral": {
        "total_referees": 2,
        "total_referral_volume": 0.0,
        "referral_fee_paid": NaN
      },
      "last_updated": "2026-04-17T01:21:54.110781+00:00"
    },
    {
      "address": "0x5beF93fbe182Ece9776f255b05005b81305F90bf",
      "name": "Roundtrip",
      "refcode": "",
      "pear": {
        "total_volume": 846614.89,
        "total_fees": 873.0488,
        "total_builder_fees": 503.1964
      },
      "referral": {
        "total_referees": 1,
        "total_referral_volume": 0.0,
        "referral_fee_paid": 1000.0
      },
      "last_updated": "2026-04-17T01:21:55.852616+00:00"
    },
    {
      "address": "0x6334546f6D6079d6276C8124389decF4C7A26d12",
      "name": "Pasta Capital",
      "refcode": "",
      "pear": {
        "total_volume": 28459.41,
        "total_fees": 27.8279,
        "total_builder_fees": 15.5283
      },
      "referral": {
        "total_referees": 9,
        "total_referral_volume": 0.0,
        "referral_fee_paid": NaN
      },
      "last_updated": "2026-04-17T01:21:58.468281+00:00"
    },
    {
      "address": "0xd38c2a7f39acb6fc5c8c81803f883dc2e7ba6210",
      "name": "Wunder",
      "refcode": "",
      "pear": {
        "total_volume": 32092.5,
        "total_fees": 33.1029,
        "total_builder_fees": 19.2554
      },
      "referral": {
        "total_referees": 2,
        "total_referral_volume": 0.0,
        "referral_fee_paid": NaN
      },
      "last_updated": "2026-04-17T01:22:00.182008+00:00"
    },
    {
      "address": "0x02689fb31aC9919820512164D007F8b757bd4E60",
      "name": "Jorge",
      "refcode": "",
      "pear": {
        "total_volume": 72519.19,
        "total_fees": 66.5581,
        "total_builder_fees": 43.4715
      },
      "referral": {
        "total_referees": 0,
        "total_referral_volume": 0.0,
        "referral_fee_paid": NaN
      },
      "last_updated": "2026-04-17T01:22:01.538141+00:00"
    },
    {
      "address": "0xf849FbC43f9a108A297c8730eEdE2896932fda68",
      "name": "CC intern",
      "refcode": "",
      "pear": {
        "total_volume": 1007.13,
        "total_fees": 0.6949,
        "total_builder_fees": 0.6043
      },
      "referral": {
        "total_referees": 0,
        "total_referral_volume": 0.0,
        "referral_fee_paid": NaN
      },
      "last_updated": "2026-04-17T01:22:03.109207+00:00"
    },
    {
      "address": "0x7bDCA5825c9B78Cab7672E91BDa91588b06322DB",
      "name": "Ray Tio",
      "refcode": "",
      "pear": {
        "total_volume": 28472.97,
        "total_fees": 34.2664,
        "total_builder_fees": 16.6509
      },
      "referral": {
        "total_referees": 0,
        "total_referral_volume": 0.0,
        "referral_fee_paid": NaN
      },
      "last_updated": "2026-04-17T01:22:04.447635+00:00"
    },
    {
      "address": "0xc89BC727d388bB74E9Db02BBc00c14e4dB27fd80",
      "name": "Thatboi",
      "refcode": "",
      "pear": {
        "total_volume": 196614.98,
        "total_fees": 253.5628,
        "total_builder_fees": 117.9686
      },
      "referral": {
        "total_referees": 0,
        "total_referral_volume": 0.0,
        "referral_fee_paid": NaN
      },
      "last_updated": "2026-04-17T01:22:05.803734+00:00"
    },
    {
      "address": "0x087cdae4009af7974fb808cd4e01414ebf820ab0",
      "name": "New Era",
      "refcode": "",
      "pear": {
        "total_volume": 204563.91,
        "total_fees": 200.3762,
        "total_builder_fees": 120.9922
      },
      "referral": {
        "total_referees": 4,
        "total_referral_volume": 15891.03,
        "referral_fee_paid": NaN
      },
      "last_updated": "2026-04-17T01:22:10.016302+00:00"
    },
    {
      "address": "0x14Afd469c7f42B1c4f8927F1bA4fE0484bcb4087",
      "name": "razor.hl",
      "refcode": "",
      "pear": {
        "total_volume": 471716.41,
        "total_fees": 455.8636,
        "total_builder_fees": 283.0292
      },
      "referral": {
        "total_referees": 1,
        "total_referral_volume": 8152.04,
        "referral_fee_paid": NaN
      },
      "last_updated": "2026-04-17T01:22:14.016373+00:00"
    },
    {
      "address": "0x337959a0a270493d2d596bdf1edeb8a9643be996",
      "name": "Derivative monkey",
      "refcode": "",
      "pear": {
        "total_volume": 85267.85,
        "total_fees": 87.2807,
        "total_builder_fees": 51.0507
      },
      "referral": {
        "total_referees": 13,
        "total_referral_volume": 595974.62,
        "referral_fee_paid": NaN
      },
      "last_updated": "2026-04-17T01:22:20.297181+00:00"
    },
    {
      "address": "0xdf89d8A34Caa0673A403d9BfE239F7b199bb4A25",
      "name": "Be more Crypto.hl",
      "refcode": "",
      "pear": {
        "total_volume": 309739.3,
        "total_fees": 268.9105,
        "total_builder_fees": 184.615
      },
      "referral": {
        "total_referees": 0,
        "total_referral_volume": 0.0,
        "referral_fee_paid": NaN
      },
      "last_updated": "2026-04-17T01:22:21.657069+00:00"
    },
    {
      "address": "0xf2cEc9b717150080C5b0924740F7f3c65f7cBAe7",
      "name": "Jojo",
      "refcode": "",
      "pear": {
        "total_volume": 0.0,
        "total_fees": 0.0,
        "total_builder_fees": 0.0
      },
      "referral": {
        "total_referees": 1,
        "total_referral_volume": 0.0,
        "referral_fee_paid": NaN
      },
      "last_updated": "2026-04-17T01:22:25.528610+00:00"
    },
    {
      "address": "0xA44E8B9522A5F710e2b63aB790465af2f155b632",
      "name": "Black cat",
      "refcode": "",
      "pear": {
        "total_volume": 1514175.64,
        "total_fees": 1506.1876,
        "total_builder_fees": 873.7769
      },
      "referral": {
        "total_referees": 16,
        "total_referral_volume": 6956642.39,
        "referral_fee_paid": 660.0
      },
      "last_updated": "2026-04-17T01:22:31.005320+00:00"
    },
    {
      "address": "0x307538d1fF324E77E5eB202e5Aca37E0BAd359d6",
      "name": "zipper.hl",
      "refcode": "",
      "pear": {
        "total_volume": 5487.39,
        "total_fees": 6.1486,
        "total_builder_fees": 3.2924
      },
      "referral": {
        "total_referees": 0,
        "total_referral_volume": 0.0,
        "referral_fee_paid": NaN
      },
      "last_updated": "2026-04-17T01:22:32.599436+00:00"
    },
    {
      "address": "0x4b55D704C99891BAd4a7AC7b64f82Cef76eb0bfF",
      "name": "Dead cat bound",
      "refcode": "",
      "pear": {
        "total_volume": 53207.8,
        "total_fees": 54.9102,
        "total_builder_fees": 31.9246
      },
      "referral": {
        "total_referees": 2,
        "total_referral_volume": 0.0,
        "referral_fee_paid": NaN
      },
      "last_updated": "2026-04-17T01:22:34.342187+00:00"
    }
  ]
}