{
  "generated_at": "2026-06-04T03:02:35.162380+00:00",
  "count": 25,
  "data": [
    {
      "address": "0x8954B0745A12E6e01Bc73856D934A784064Baa78",
      "name": "Vivid.hl",
      "pear": {
        "total_volume": 2406.91,
        "total_fees": 2.5701,
        "total_builder_fees": 1.4441
      },
      "rebates_paid": NaN,
      "last_updated": "2026-06-04T03:02:35.161969+00:00"
    },
    {
      "address": "0x7C930969FCF3e5a5c78bcF2e1cefda3f53E3C8FD",
      "name": "Hyperliquidated",
      "pear": {
        "total_volume": 0.0,
        "total_fees": 0.0,
        "total_builder_fees": 0.0
      },
      "rebates_paid": NaN,
      "last_updated": "2026-06-04T03:02:35.161990+00:00"
    },
    {
      "address": "0xB8fb427A45C832c5dAc625aA7bfad720CA8C28A6",
      "name": "Wilko",
      "pear": {
        "total_volume": 12495599.23,
        "total_fees": 11575.618,
        "total_builder_fees": 7497.3554
      },
      "rebates_paid": 4900.0,
      "last_updated": "2026-06-04T03:02:35.162000+00:00"
    },
    {
      "address": "0xe6caf898d70a0f0365ae8c6211ade489025aa1bb",
      "name": "Cactus",
      "pear": {
        "total_volume": 124327794.71,
        "total_fees": 118512.949,
        "total_builder_fees": 74514.2432
      },
      "rebates_paid": NaN,
      "last_updated": "2026-06-04T03:02:35.162009+00:00"
    },
    {
      "address": "0xc4B4D58b7c5838efe8034b28c5eB6B64E33CC189",
      "name": "Sendora Fulton/Full Send",
      "pear": {
        "total_volume": 48852551.86,
        "total_fees": 46138.636,
        "total_builder_fees": 28584.782
      },
      "rebates_paid": NaN,
      "last_updated": "2026-06-04T03:02:35.162018+00:00"
    },
    {
      "address": "0x98aBb17006aaA4f29F60cb8C9C3dB70B174EbA24",
      "name": "Juan",
      "pear": {
        "total_volume": 312171.24,
        "total_fees": 232.7111,
        "total_builder_fees": 186.3024
      },
      "rebates_paid": NaN,
      "last_updated": "2026-06-04T03:02:35.162027+00:00"
    },
    {
      "address": "0x2D87C160aedD8FfE2b5d24e460bAf51F43EA61D1",
      "name": "Wilko Ref 1",
      "pear": {
        "total_volume": 5145512.92,
        "total_fees": 5181.4964,
        "total_builder_fees": 3067.7164
      },
      "rebates_paid": NaN,
      "last_updated": "2026-06-04T03:02:35.162035+00:00"
    },
    {
      "address": "0x7bDCA5825c9B78Cab7672E91BDa91588b06322DB",
      "name": "Wilko Ref 2",
      "pear": {
        "total_volume": 44978.31,
        "total_fees": 56.3224,
        "total_builder_fees": 26.5541
      },
      "rebates_paid": NaN,
      "last_updated": "2026-06-04T03:02:35.162042+00:00"
    },
    {
      "address": "0xc36f2fe0f39a46a45c89bbF92D2531F7D1389062",
      "name": "Col3",
      "pear": {
        "total_volume": 62326182.49,
        "total_fees": 58088.5957,
        "total_builder_fees": 37035.7977
      },
      "rebates_paid": NaN,
      "last_updated": "2026-06-04T03:02:35.162050+00:00"
    },
    {
      "address": "0x171b7880939d76abbc6b6b2094f54e6636f829a7",
      "name": "Unidentified Whale 1",
      "pear": {
        "total_volume": 4088739.87,
        "total_fees": 2934.9428,
        "total_builder_fees": 2446.2037
      },
      "rebates_paid": NaN,
      "last_updated": "2026-06-04T03:02:35.162057+00:00"
    },
    {
      "address": "0x82590d058ddb9b6d81cea05f0c500e981755bb0b",
      "name": "Wilko friend (Save the Whale)",
      "pear": {
        "total_volume": 179603.16,
        "total_fees": 188.5832,
        "total_builder_fees": 107.7618
      },
      "rebates_paid": NaN,
      "last_updated": "2026-06-04T03:02:35.162065+00:00"
    },
    {
      "address": "0x1bc73b7556a79a3e6ee1a09044cb593b7663349b",
      "name": "Unidentified Whale 2",
      "pear": {
        "total_volume": 2980518.59,
        "total_fees": 2551.4264,
        "total_builder_fees": 1785.3097
      },
      "rebates_paid": NaN,
      "last_updated": "2026-06-04T03:02:35.162072+00:00"
    },
    {
      "address": "0x955dfb921c6e481bf26225282720dba9196c3441",
      "name": "Unidentified Whale 3",
      "pear": {
        "total_volume": 10840054.69,
        "total_fees": 11290.9102,
        "total_builder_fees": 6504.0119
      },
      "rebates_paid": NaN,
      "last_updated": "2026-06-04T03:02:35.162080+00:00"
    },
    {
      "address": "0x8be269D1F0731e7c2990558d2AF0D8A4A99D0eC4",
      "name": "Thinker",
      "pear": {
        "total_volume": 4601135.23,
        "total_fees": 3296.2727,
        "total_builder_fees": 2760.6799
      },
      "rebates_paid": 690.0,
      "last_updated": "2026-06-04T03:02:35.162088+00:00"
    },
    {
      "address": "0x6ee5aee6c8148285f4d156b5b5732659c6f7bb4c",
      "name": "H1",
      "pear": {
        "total_volume": 10677080.87,
        "total_fees": 10936.0173,
        "total_builder_fees": 6401.3343
      },
      "rebates_paid": NaN,
      "last_updated": "2026-06-04T03:02:35.162096+00:00"
    },
    {
      "address": "0x82211560d304a632820674b9fc98ab81e4a7d403",
      "name": "H2",
      "pear": {
        "total_volume": 15800277.15,
        "total_fees": 16319.8803,
        "total_builder_fees": 9480.1617
      },
      "rebates_paid": NaN,
      "last_updated": "2026-06-04T03:02:35.162104+00:00"
    },
    {
      "address": "0x7104E77dcf3872DbE7868ecb321b8F72be92B9a1",
      "name": "Juan #2",
      "pear": {
        "total_volume": 201347.32,
        "total_fees": 178.9165,
        "total_builder_fees": 120.8077
      },
      "rebates_paid": NaN,
      "last_updated": "2026-06-04T03:02:35.162112+00:00"
    },
    {
      "address": "0x18e41bb2205e0d87ce94474411d49c035c15b062",
      "name": "Red40 / flaustrian",
      "pear": {
        "total_volume": 14746719.88,
        "total_fees": 14917.1341,
        "total_builder_fees": 8843.8097
      },
      "rebates_paid": NaN,
      "last_updated": "2026-06-04T03:02:35.162119+00:00"
    },
    {
      "address": "0xe9683ec9a1c66fd9c394ccfed822a4de82b1792e",
      "name": "Unidentified Whale 6",
      "pear": {
        "total_volume": 1030720.91,
        "total_fees": 1063.7032,
        "total_builder_fees": 618.4322
      },
      "rebates_paid": NaN,
      "last_updated": "2026-06-04T03:02:35.162127+00:00"
    },
    {
      "address": "0x97bff6e46d556ad271f2b1d048c9129cdcf03e2f",
      "name": "Unidentified Whale 7",
      "pear": {
        "total_volume": 18164204.16,
        "total_fees": 17731.8399,
        "total_builder_fees": 10898.5176
      },
      "rebates_paid": NaN,
      "last_updated": "2026-06-04T03:02:35.162134+00:00"
    },
    {
      "address": "0xe49a765141e447864cd0f211811b93aac7d94901",
      "name": "Pearsistent",
      "pear": {
        "total_volume": 2520910.13,
        "total_fees": 2550.0244,
        "total_builder_fees": 1474.0073
      },
      "rebates_paid": NaN,
      "last_updated": "2026-06-04T03:02:35.162141+00:00"
    },
    {
      "address": "0x17DfAEFF54c975ff8871944Da9CE2b10cdf4f184",
      "name": "CryptoCow",
      "pear": {
        "total_volume": 7717293.06,
        "total_fees": 8013.2913,
        "total_builder_fees": 4574.2735
      },
      "rebates_paid": NaN,
      "last_updated": "2026-06-04T03:02:35.162149+00:00"
    },
    {
      "address": "0xc7ae23316b47f7e75f455f53ad37873a18351505",
      "name": "Unidentified Whale 8",
      "pear": {
        "total_volume": 1661306.08,
        "total_fees": 1642.5582,
        "total_builder_fees": 987.9751
      },
      "rebates_paid": NaN,
      "last_updated": "2026-06-04T03:02:35.162156+00:00"
    },
    {
      "address": "0x8a561555BeBE4BfE57B598773304Ce935f9Eb80C",
      "name": "Eva",
      "pear": {
        "total_volume": 204447.88,
        "total_fees": 195.3995,
        "total_builder_fees": 122.6686
      },
      "rebates_paid": NaN,
      "last_updated": "2026-06-04T03:02:35.162163+00:00"
    },
    {
      "address": "0xC38a3879C4DcdAF97CecCa6cd3C19Fd6539A7aEd",
      "name": "Jore",
      "pear": {
        "total_volume": 2240772.71,
        "total_fees": 2296.7444,
        "total_builder_fees": 1344.4628
      },
      "rebates_paid": NaN,
      "last_updated": "2026-06-04T03:02:35.162170+00:00"
    }
  ]
}